{
  "lastUpdate": "18.10.2025",
  "dams": [
    {
      "id": "1",
      "name": "Idukki",
      "date": "18.10.2025",
      "level": 725.98,
      "inflow": 11.1,
      "outflow": 128.45,
      "rainfall": 7.01,
      "status": "1106.30",
      "frl": 732.43,
      "mwl": 731.17,
      "lat": 9.8436,
      "lon": 76.9762,
      "district": "Idukki",
      "capacity": 1996,
      "data": [
        {
          "date": "18.10.2025",
          "waterLevel": "2381.82 ft",
          "liveStorage": "1106.30",
          "storagePercentage": "75.80",
          "inflow": "11.10",
          "powerHouseDischarge": "7.01",
          "spillwayRelease": "–",
          "totalOutflow": "7.01",
          "rainfall": "31.80"
        }
      ]
    },
    {
      "id": "2",
      "name": "Idamalayar",
      "date": "18.10.2025",
      "level": 49.05,
      "inflow": 7.86,
      "outflow": 91.02,
      "rainfall": 4.47,
      "status": "786.32",
      "frl": 51.51,
      "mwl": 50.84,
      "lat": 10.2219,
      "lon": 76.706,
      "district": "Ernakulam",
      "capacity": 1010,
      "data": [
        {
          "date": "18.10.2025",
          "waterLevel": "160.94",
          "liveStorage": "786.32",
          "storagePercentage": "77.26",
          "inflow": "7.86",
          "powerHouseDischarge": "4.47",
          "spillwayRelease": "–",
          "totalOutflow": "4.47",
          "rainfall": "51.80"
        }
      ]
    },
    {
      "id": "4",
      "name": "Banasura Sagar",
      "date": "18.10.2025",
      "level": 235.67,
      "inflow": 0.42,
      "outflow": 4.86,
      "rainfall": 1.02,
      "status": "171.75",
      "frl": 236.4,
      "mwl": 236.4,
      "lat": 11.6709,
      "lon": 75.9504,
      "district": "Wayanad",
      "capacity": 209,
      "data": [
        {
          "date": "18.10.2025",
          "waterLevel": "773.20",
          "liveStorage": "171.75",
          "storagePercentage": "85.45",
          "inflow": "0.42",
          "powerHouseDischarge": "1.02",
          "spillwayRelease": "–",
          "totalOutflow": "1.02",
          "rainfall": "9.40"
        }
      ]
    },
    {
      "id": "5",
      "name": "Sholayar",
      "date": "18.10.2025",
      "level": 810.83,
      "inflow": 1.07,
      "outflow": 12.34,
      "rainfall": 1.35,
      "status": "141.18",
      "frl": 811.68,
      "mwl": null,
      "lat": 10.3178,
      "lon": 76.7342,
      "district": "Thrissur",
      "capacity": 1530,
      "data": [
        {
          "date": "18.10.2025",
          "waterLevel": "2660.20 ft",
          "liveStorage": "141.18",
          "storagePercentage": "94.70",
          "inflow": "1.07",
          "powerHouseDischarge": "1.35",
          "spillwayRelease": "–",
          "totalOutflow": "1.35",
          "rainfall": "25.00"
        }
      ]
    },
    {
      "id": "6",
      "name": "Mattupetty",
      "date": "18.10.2025",
      "level": 486.52,
      "inflow": 1.24,
      "outflow": 14.34,
      "rainfall": null,
      "status": "45.44",
      "frl": 487.56,
      "mwl": null,
      "lat": 10.1063,
      "lon": 77.1238,
      "district": "Idukki",
      "capacity": 55,
      "data": [
        {
          "date": "18.10.2025",
          "waterLevel": "1596.20",
          "liveStorage": "45.44",
          "storagePercentage": "82.97",
          "inflow": "1.24",
          "powerHouseDischarge": "0.00",
          "spillwayRelease": "0.95",
          "totalOutflow": "0.95",
          "rainfall": "40.40"
        }
      ]
    },
    {
      "id": "7",
      "name": "Anayirankal",
      "date": "18.10.2025",
      "level": 367.95,
      "inflow": 0.31,
      "outflow": 3.64,
      "rainfall": null,
      "status": "50.66",
      "frl": 367.9,
      "mwl": null,
      "lat": 10.0095,
      "lon": 77.2072,
      "district": "Idukki",
      "capacity": 50,
      "data": [
        {
          "date": "18.10.2025",
          "waterLevel": "1207.18",
          "liveStorage": "50.66",
          "storagePercentage": "101.67",
          "inflow": "0.31",
          "powerHouseDischarge": "",
          "spillwayRelease": "0.26",
          "totalOutflow": "0.00",
          "rainfall": "45.00"
        }
      ]
    },
    {
      "id": "8",
      "name": "Ponmudi",
      "date": "18.10.2025",
      "level": 214.41,
      "inflow": 2.64,
      "outflow": 30.6,
      "rainfall": 1.75,
      "status": "37.04",
      "frl": 215.72,
      "mwl": null,
      "lat": 9.9604,
      "lon": 77.0565,
      "district": "Idukki",
      "capacity": 42,
      "data": [
        {
          "date": "18.10.2025",
          "waterLevel": "703.45",
          "liveStorage": "37.04",
          "storagePercentage": "78.14",
          "inflow": "2.64",
          "powerHouseDischarge": "1.75",
          "spillwayRelease": "–",
          "totalOutflow": "1.75",
          "rainfall": "48.00"
        }
      ]
    },
    {
      "id": "9",
      "name": "Kakkayam",
      "date": "18.10.2025",
      "level": 230.33,
      "inflow": 1.52,
      "outflow": 17.64,
      "rainfall": 1.83,
      "status": "28.04",
      "frl": 231.05,
      "mwl": null,
      "lat": 11.551,
      "lon": 75.925,
      "district": "Kozhikode",
      "capacity": 136,
      "data": [
        {
          "date": "18.10.2025",
          "waterLevel": "755.66",
          "liveStorage": "28.04",
          "storagePercentage": "82.52",
          "inflow": "1.52",
          "powerHouseDischarge": "1.83",
          "spillwayRelease": "–",
          "totalOutflow": "1.83",
          "rainfall": "11.00"
        }
      ]
    },
    {
      "id": "10",
      "name": "Pamba",
      "date": "18.10.2025",
      "level": 297.99,
      "inflow": 3.32,
      "outflow": 38.46,
      "rainfall": null,
      "status": "16.11",
      "frl": 300.63,
      "mwl": null,
      "lat": 9.3906,
      "lon": 77.1598,
      "district": "Pathanamthitta",
      "capacity": 37,
      "data": [
        {
          "date": "18.10.2025",
          "waterLevel": "977.65",
          "liveStorage": "16.11",
          "storagePercentage": "51.72",
          "inflow": "3.32",
          "powerHouseDischarge": "",
          "spillwayRelease": "–",
          "totalOutflow": "0.00",
          "rainfall": "107.00"
        }
      ]
    },
    {
      "id": "11",
      "name": "Poringalkuthu",
      "date": "18.10.2025",
      "level": 127.67,
      "inflow": 3.28,
      "outflow": 37.96,
      "rainfall": 2.53,
      "status": "16.93",
      "frl": 129.23,
      "mwl": null,
      "lat": 10.3436,
      "lon": 76.7438,
      "district": "Thrissur",
      "capacity": 328,
      "data": [
        {
          "date": "18.10.2025",
          "waterLevel": "418.85",
          "liveStorage": "16.93",
          "storagePercentage": "55.87",
          "inflow": "3.28",
          "powerHouseDischarge": "2.53",
          "spillwayRelease": "–",
          "totalOutflow": "2.53",
          "rainfall": "39.20"
        }
      ]
    },
    {
      "id": "12",
      "name": "Kundala",
      "date": "18.10.2025",
      "level": 535.88,
      "inflow": 0.13,
      "outflow": 1.56,
      "rainfall": null,
      "status": "7.01",
      "frl": 536.05,
      "mwl": null,
      "lat": 10.1436,
      "lon": 77.1986,
      "district": "Idukki",
      "capacity": 14,
      "data": [
        {
          "date": "18.10.2025",
          "waterLevel": "1758.15",
          "liveStorage": "7.01",
          "storagePercentage": "91.57",
          "inflow": "0.13",
          "powerHouseDischarge": "0.00",
          "spillwayRelease": "0.03",
          "totalOutflow": "0.03",
          "rainfall": "68.40"
        }
      ]
    },
    {
      "id": "13",
      "name": "Kallarkutty",
      "date": "18.10.2025",
      "level": 138.07,
      "inflow": 3.56,
      "outflow": 41.21,
      "rainfall": 3.41,
      "status": "4.22",
      "frl": 139.17,
      "mwl": null,
      "lat": 9.98,
      "lon": 77.0014,
      "district": "Idukki",
      "capacity": 44,
      "data": [
        {
          "date": "18.10.2025",
          "waterLevel": "453.00",
          "liveStorage": "4.22",
          "storagePercentage": "65.61",
          "inflow": "3.56",
          "powerHouseDischarge": "3.41",
          "spillwayRelease": "–",
          "totalOutflow": "3.41",
          "rainfall": "37.00"
        }
      ]
    },
    {
      "id": "14",
      "name": "Erattayar",
      "date": "18.10.2025",
      "level": 228.75,
      "inflow": null,
      "outflow": null,
      "rainfall": null,
      "status": "2.49",
      "frl": 229.94,
      "mwl": null,
      "lat": 9.8103,
      "lon": 77.106,
      "district": "Idukki",
      "capacity": 65,
      "data": [
        {
          "date": "18.10.2025",
          "waterLevel": "750.50",
          "liveStorage": "2.49",
          "storagePercentage": "46.97",
          "inflow": "",
          "powerHouseDischarge": "",
          "spillwayRelease": "",
          "totalOutflow": "0.00",
          "rainfall": ""
        }
      ]
    },
    {
      "id": "15",
      "name": "Pambla",
      "date": "18.10.2025",
      "level": 75.83,
      "inflow": 5.89,
      "outflow": 68.18,
      "rainfall": 5.06,
      "status": "2.82",
      "frl": 77.11,
      "mwl": null,
      "lat": 9.962,
      "lon": 76.9568,
      "district": "Ernakulam",
      "capacity": 23,
      "data": [
        {
          "date": "18.10.2025",
          "waterLevel": "248.80",
          "liveStorage": "2.82",
          "storagePercentage": "62.02",
          "inflow": "5.89",
          "powerHouseDischarge": "5.06",
          "spillwayRelease": "–",
          "totalOutflow": "5.06",
          "rainfall": "27.00"
        }
      ]
    },
    {
      "id": "16",
      "name": "Moozhiyar",
      "date": "18.10.2025",
      "level": 57.7,
      "inflow": 3,
      "outflow": 34.75,
      "rainfall": 2.33,
      "status": "0.72",
      "frl": 58.71,
      "mwl": null,
      "lat": 9.308,
      "lon": 77.0656,
      "district": "Pathanamthitta",
      "capacity": 90,
      "data": [
        {
          "date": "18.10.2025",
          "waterLevel": "189.30",
          "liveStorage": "0.72",
          "storagePercentage": "61.64",
          "inflow": "3.00",
          "powerHouseDischarge": "2.33",
          "spillwayRelease": "–",
          "totalOutflow": "2.33",
          "rainfall": "38.00"
        }
      ]
    },
    {
      "id": "17",
      "name": "Kallar",
      "date": "18.10.2025",
      "level": 251.12,
      "inflow": null,
      "outflow": null,
      "rainfall": null,
      "status": "0.60",
      "frl": 251.3,
      "mwl": null,
      "lat": 9.8255,
      "lon": 77.1562,
      "district": "Idukki",
      "capacity": 14,
      "data": [
        {
          "date": "18.10.2025",
          "waterLevel": "823.90",
          "liveStorage": "0.60",
          "storagePercentage": "78.35",
          "inflow": "",
          "powerHouseDischarge": "",
          "spillwayRelease": "–",
          "totalOutflow": "0.00",
          "rainfall": ""
        }
      ]
    },
    {
      "id": "18",
      "name": "Chenkulam",
      "date": "18.10.2025",
      "level": 258.15,
      "inflow": 1.16,
      "outflow": 13.44,
      "rainfall": 1.13,
      "status": "0.23",
      "frl": 258.36,
      "mwl": null,
      "lat": 10.0108,
      "lon": 77.0325,
      "district": "Idukki",
      "capacity": 16,
      "data": [
        {
          "date": "18.10.2025",
          "waterLevel": "846.95",
          "liveStorage": "0.23",
          "storagePercentage": "57.69",
          "inflow": "1.16",
          "powerHouseDischarge": "1.13",
          "spillwayRelease": "–",
          "totalOutflow": "1.13",
          "rainfall": "2.60"
        }
      ]
    }
  ]
}