{
  "lastUpdate": "31.10.2025",
  "dams": [
    {
      "id": "1",
      "name": "Idukki",
      "date": "31.10.2025",
      "level": 727.22,
      "inflow": 7.97,
      "outflow": 92.19,
      "rainfall": 9.17,
      "status": "1173.85",
      "frl": 732.43,
      "mwl": 731.31,
      "lat": 9.8436,
      "lon": 76.9762,
      "district": "Idukki",
      "capacity": 1996,
      "data": [
        {
          "date": "31.10.2025",
          "waterLevel": "2385.90 ft",
          "liveStorage": "1173.85",
          "storagePercentage": "80.43",
          "inflow": "7.97",
          "powerHouseDischarge": "9.17",
          "spillwayRelease": "–",
          "totalOutflow": "9.17",
          "rainfall": "0.00"
        }
      ]
    },
    {
      "id": "2",
      "name": "Idamalayar",
      "date": "31.10.2025",
      "level": 49.27,
      "inflow": 3.18,
      "outflow": 36.8,
      "rainfall": 2.53,
      "status": "806.68",
      "frl": 51.51,
      "mwl": 50.9,
      "lat": 10.2219,
      "lon": 76.706,
      "district": "Ernakulam",
      "capacity": 1010,
      "data": [
        {
          "date": "31.10.2025",
          "waterLevel": "161.66",
          "liveStorage": "806.68",
          "storagePercentage": "79.26",
          "inflow": "3.18",
          "powerHouseDischarge": "2.53",
          "spillwayRelease": "–",
          "totalOutflow": "2.53",
          "rainfall": "0.00"
        }
      ]
    },
    {
      "id": "4",
      "name": "Banasura Sagar",
      "date": "31.10.2025",
      "level": 235.81,
      "inflow": 0.43,
      "outflow": 4.98,
      "rainfall": null,
      "status": "177.15",
      "frl": 236.4,
      "mwl": 236.4,
      "lat": 11.6709,
      "lon": 75.9504,
      "district": "Wayanad",
      "capacity": 209,
      "data": [
        {
          "date": "31.10.2025",
          "waterLevel": "773.65",
          "liveStorage": "177.15",
          "storagePercentage": "88.13",
          "inflow": "0.43",
          "powerHouseDischarge": "",
          "spillwayRelease": "–",
          "totalOutflow": "0.00",
          "rainfall": "0.00"
        }
      ]
    },
    {
      "id": "5",
      "name": "Sholayar",
      "date": "31.10.2025",
      "level": 811.04,
      "inflow": 0.58,
      "outflow": 6.66,
      "rainfall": 0.58,
      "status": "143.15",
      "frl": 811.68,
      "mwl": null,
      "lat": 10.3178,
      "lon": 76.7342,
      "district": "Thrissur",
      "capacity": 1530,
      "data": [
        {
          "date": "31.10.2025",
          "waterLevel": "2660.90 ft",
          "liveStorage": "143.15",
          "storagePercentage": "96.02",
          "inflow": "0.58",
          "powerHouseDischarge": "0.58",
          "spillwayRelease": "–",
          "totalOutflow": "0.58",
          "rainfall": "0.00"
        }
      ]
    },
    {
      "id": "6",
      "name": "Mattupetty",
      "date": "31.10.2025",
      "level": 486.61,
      "inflow": 0.42,
      "outflow": 4.88,
      "rainfall": 0.53,
      "status": "46.19",
      "frl": 487.56,
      "mwl": null,
      "lat": 10.1063,
      "lon": 77.1238,
      "district": "Idukki",
      "capacity": 55,
      "data": [
        {
          "date": "31.10.2025",
          "waterLevel": "1596.50",
          "liveStorage": "46.19",
          "storagePercentage": "84.33",
          "inflow": "0.42",
          "powerHouseDischarge": "0.53",
          "spillwayRelease": "–",
          "totalOutflow": "0.53",
          "rainfall": "0.00"
        }
      ]
    },
    {
      "id": "7",
      "name": "Anayirankal",
      "date": "31.10.2025",
      "level": 367.94,
      "inflow": 0.19,
      "outflow": 2.24,
      "rainfall": null,
      "status": "50.56",
      "frl": 367.9,
      "mwl": null,
      "lat": 10.0095,
      "lon": 77.2072,
      "district": "Idukki",
      "capacity": 50,
      "data": [
        {
          "date": "31.10.2025",
          "waterLevel": "1207.16",
          "liveStorage": "50.56",
          "storagePercentage": "101.46",
          "inflow": "0.19",
          "powerHouseDischarge": "",
          "spillwayRelease": "0.25",
          "totalOutflow": "0.25",
          "rainfall": "0.00"
        }
      ]
    },
    {
      "id": "8",
      "name": "Ponmudi",
      "date": "31.10.2025",
      "level": 215.36,
      "inflow": 2.26,
      "outflow": 26.14,
      "rainfall": 1.76,
      "status": "44.03",
      "frl": 215.72,
      "mwl": null,
      "lat": 9.9604,
      "lon": 77.0565,
      "district": "Idukki",
      "capacity": 42,
      "data": [
        {
          "date": "31.10.2025",
          "waterLevel": "706.55",
          "liveStorage": "44.03",
          "storagePercentage": "92.90",
          "inflow": "2.26",
          "powerHouseDischarge": "1.76",
          "spillwayRelease": "0.66",
          "totalOutflow": "2.42",
          "rainfall": "0.00"
        }
      ]
    },
    {
      "id": "9",
      "name": "Kakkayam",
      "date": "31.10.2025",
      "level": 230.33,
      "inflow": 1.76,
      "outflow": 20.4,
      "rainfall": 1.23,
      "status": "28.12",
      "frl": 231.05,
      "mwl": null,
      "lat": 11.551,
      "lon": 75.925,
      "district": "Kozhikode",
      "capacity": 136,
      "data": [
        {
          "date": "31.10.2025",
          "waterLevel": "755.69",
          "liveStorage": "28.12",
          "storagePercentage": "82.74",
          "inflow": "1.76",
          "powerHouseDischarge": "1.23",
          "spillwayRelease": "–",
          "totalOutflow": "1.23",
          "rainfall": "0.00"
        }
      ]
    },
    {
      "id": "10",
      "name": "Pamba",
      "date": "31.10.2025",
      "level": 298.57,
      "inflow": 1.33,
      "outflow": 15.39,
      "rainfall": null,
      "status": "18.96",
      "frl": 300.63,
      "mwl": null,
      "lat": 9.3906,
      "lon": 77.1598,
      "district": "Pathanamthitta",
      "capacity": 37,
      "data": [
        {
          "date": "31.10.2025",
          "waterLevel": "979.55",
          "liveStorage": "18.96",
          "storagePercentage": "60.87",
          "inflow": "1.33",
          "powerHouseDischarge": "",
          "spillwayRelease": "–",
          "totalOutflow": "0.00",
          "rainfall": "0.00"
        }
      ]
    },
    {
      "id": "11",
      "name": "Poringalkuthu",
      "date": "31.10.2025",
      "level": 128,
      "inflow": 2.52,
      "outflow": 29.2,
      "rainfall": 2.9,
      "status": "19.63",
      "frl": 129.23,
      "mwl": null,
      "lat": 10.3436,
      "lon": 76.7438,
      "district": "Thrissur",
      "capacity": 328,
      "data": [
        {
          "date": "31.10.2025",
          "waterLevel": "419.95",
          "liveStorage": "19.63",
          "storagePercentage": "64.79",
          "inflow": "2.52",
          "powerHouseDischarge": "2.90",
          "spillwayRelease": "–",
          "totalOutflow": "2.90",
          "rainfall": "0.00"
        }
      ]
    },
    {
      "id": "12",
      "name": "Kundala",
      "date": "31.10.2025",
      "level": 535.85,
      "inflow": 0.03,
      "outflow": 0.34,
      "rainfall": null,
      "status": "6.94",
      "frl": 536.05,
      "mwl": null,
      "lat": 10.1436,
      "lon": 77.1986,
      "district": "Idukki",
      "capacity": 14,
      "data": [
        {
          "date": "31.10.2025",
          "waterLevel": "1758.05",
          "liveStorage": "6.94",
          "storagePercentage": "90.65",
          "inflow": "0.03",
          "powerHouseDischarge": "0.00",
          "spillwayRelease": "0.03",
          "totalOutflow": "0.03",
          "rainfall": "0.00"
        }
      ]
    },
    {
      "id": "13",
      "name": "Kallarkutty",
      "date": "31.10.2025",
      "level": 139.02,
      "inflow": 5.25,
      "outflow": 60.72,
      "rainfall": 3.87,
      "status": "6.16",
      "frl": 139.17,
      "mwl": null,
      "lat": 9.98,
      "lon": 77.0014,
      "district": "Idukki",
      "capacity": 44,
      "data": [
        {
          "date": "31.10.2025",
          "waterLevel": "456.10",
          "liveStorage": "6.16",
          "storagePercentage": "95.74",
          "inflow": "5.25",
          "powerHouseDischarge": "3.87",
          "spillwayRelease": "1.58",
          "totalOutflow": "5.45",
          "rainfall": "0.00"
        }
      ]
    },
    {
      "id": "14",
      "name": "Erattayar",
      "date": "31.10.2025",
      "level": 227.81,
      "inflow": null,
      "outflow": null,
      "rainfall": null,
      "status": "1.09",
      "frl": 229.94,
      "mwl": null,
      "lat": 9.8103,
      "lon": 77.106,
      "district": "Idukki",
      "capacity": 65,
      "data": [
        {
          "date": "31.10.2025",
          "waterLevel": "747.40",
          "liveStorage": "1.09",
          "storagePercentage": "20.63",
          "inflow": "",
          "powerHouseDischarge": "",
          "spillwayRelease": "",
          "totalOutflow": "0.00",
          "rainfall": ""
        }
      ]
    },
    {
      "id": "15",
      "name": "Pambla",
      "date": "31.10.2025",
      "level": 75.5,
      "inflow": 7.24,
      "outflow": 83.81,
      "rainfall": 7.88,
      "status": "2.42",
      "frl": 77.11,
      "mwl": null,
      "lat": 9.962,
      "lon": 76.9568,
      "district": "Ernakulam",
      "capacity": 23,
      "data": [
        {
          "date": "31.10.2025",
          "waterLevel": "247.70",
          "liveStorage": "2.42",
          "storagePercentage": "53.12",
          "inflow": "7.24",
          "powerHouseDischarge": "7.88",
          "spillwayRelease": "–",
          "totalOutflow": "7.88",
          "rainfall": "0.00"
        }
      ]
    },
    {
      "id": "16",
      "name": "Moozhiyar",
      "date": "31.10.2025",
      "level": 57.76,
      "inflow": 2.74,
      "outflow": 31.67,
      "rainfall": 2.7,
      "status": "0.74",
      "frl": 58.71,
      "mwl": null,
      "lat": 9.308,
      "lon": 77.0656,
      "district": "Pathanamthitta",
      "capacity": 90,
      "data": [
        {
          "date": "31.10.2025",
          "waterLevel": "189.50",
          "liveStorage": "0.74",
          "storagePercentage": "63.62",
          "inflow": "2.74",
          "powerHouseDischarge": "2.70",
          "spillwayRelease": "–",
          "totalOutflow": "2.70",
          "rainfall": "0.00"
        }
      ]
    },
    {
      "id": "17",
      "name": "Kallar",
      "date": "31.10.2025",
      "level": 250.06,
      "inflow": null,
      "outflow": null,
      "rainfall": null,
      "status": "0.20",
      "frl": 251.3,
      "mwl": null,
      "lat": 9.8255,
      "lon": 77.1562,
      "district": "Idukki",
      "capacity": 14,
      "data": [
        {
          "date": "31.10.2025",
          "waterLevel": "820.40",
          "liveStorage": "0.20",
          "storagePercentage": "26.12",
          "inflow": "",
          "powerHouseDischarge": "",
          "spillwayRelease": "–",
          "totalOutflow": "0.00",
          "rainfall": ""
        }
      ]
    },
    {
      "id": "18",
      "name": "Chenkulam",
      "date": "31.10.2025",
      "level": 258.07,
      "inflow": 1.39,
      "outflow": 16.09,
      "rainfall": 1.43,
      "status": "0.17",
      "frl": 258.36,
      "mwl": null,
      "lat": 10.0108,
      "lon": 77.0325,
      "district": "Idukki",
      "capacity": 16,
      "data": [
        {
          "date": "31.10.2025",
          "waterLevel": "846.70",
          "liveStorage": "0.17",
          "storagePercentage": "42.31",
          "inflow": "1.39",
          "powerHouseDischarge": "1.43",
          "spillwayRelease": "–",
          "totalOutflow": "1.43",
          "rainfall": "0.00"
        }
      ]
    }
  ]
}