{
  "lastUpdate": "04.06.2026",
  "dams": [
    {
      "id": "1",
      "name": "Idukki",
      "date": "04.06.2026",
      "level": 706.03,
      "inflow": 2.96,
      "outflow": 34.29,
      "rainfall": 3.72,
      "status": "299.70",
      "frl": 732.43,
      "mwl": 723.29,
      "lat": 9.8436,
      "lon": 76.9762,
      "district": "Idukki",
      "capacity": 1996,
      "data": [
        {
          "date": "04.06.2026",
          "waterLevel": "2316.36 ft",
          "liveStorage": "299.70",
          "storagePercentage": "20.53",
          "inflow": "2.96",
          "powerHouseDischarge": "3.72",
          "spillwayRelease": "–",
          "totalOutflow": "3.72",
          "rainfall": "39.20"
        }
      ]
    },
    {
      "id": "2",
      "name": "Idamalayar",
      "date": "04.06.2026",
      "level": 41.21,
      "inflow": 2.2,
      "outflow": 25.51,
      "rainfall": 1.6,
      "status": "222.85",
      "frl": 51.51,
      "mwl": 49.07,
      "lat": 10.2219,
      "lon": 76.706,
      "district": "Ernakulam",
      "capacity": 1010,
      "data": [
        {
          "date": "04.06.2026",
          "waterLevel": "135.19",
          "liveStorage": "222.85",
          "storagePercentage": "21.90",
          "inflow": "2.20",
          "powerHouseDischarge": "1.60",
          "spillwayRelease": "–",
          "totalOutflow": "1.60",
          "rainfall": "37.00"
        }
      ]
    },
    {
      "id": "4",
      "name": "Banasura Sagar",
      "date": "04.06.2026",
      "level": 229.9,
      "inflow": 0.35,
      "outflow": 4.05,
      "rainfall": null,
      "status": "12.25",
      "frl": 236.4,
      "mwl": 233.78,
      "lat": 11.6709,
      "lon": 75.9504,
      "district": "Wayanad",
      "capacity": 209,
      "data": [
        {
          "date": "04.06.2026",
          "waterLevel": "754.25",
          "liveStorage": "12.25",
          "storagePercentage": "6.09",
          "inflow": "0.35",
          "powerHouseDischarge": "",
          "spillwayRelease": "–",
          "totalOutflow": "0.00",
          "rainfall": "8.30"
        }
      ]
    },
    {
      "id": "5",
      "name": "Sholayar",
      "date": "04.06.2026",
      "level": 788.55,
      "inflow": 0.29,
      "outflow": 3.32,
      "rainfall": 0.55,
      "status": "16.96",
      "frl": 811.68,
      "mwl": null,
      "lat": 10.3178,
      "lon": 76.7342,
      "district": "Thrissur",
      "capacity": 1530,
      "data": [
        {
          "date": "04.06.2026",
          "waterLevel": "2587.10 ft",
          "liveStorage": "16.96",
          "storagePercentage": "11.38",
          "inflow": "0.29",
          "powerHouseDischarge": "0.55",
          "spillwayRelease": "–",
          "totalOutflow": "0.55",
          "rainfall": "25.00"
        }
      ]
    },
    {
      "id": "6",
      "name": "Mattupetty",
      "date": "04.06.2026",
      "level": 478.89,
      "inflow": 0.56,
      "outflow": 6.5,
      "rainfall": null,
      "status": "5.44",
      "frl": 487.56,
      "mwl": null,
      "lat": 10.1063,
      "lon": 77.1238,
      "district": "Idukki",
      "capacity": 55,
      "data": [
        {
          "date": "04.06.2026",
          "waterLevel": "1571.15",
          "liveStorage": "5.44",
          "storagePercentage": "9.93",
          "inflow": "0.56",
          "powerHouseDischarge": "0.00",
          "spillwayRelease": "–",
          "totalOutflow": "0.00",
          "rainfall": "27.00"
        }
      ]
    },
    {
      "id": "7",
      "name": "Anayirankal",
      "date": "04.06.2026",
      "level": 363.75,
      "inflow": 0.95,
      "outflow": 10.98,
      "rainfall": null,
      "status": "7.24",
      "frl": 367.9,
      "mwl": null,
      "lat": 10.0095,
      "lon": 77.2072,
      "district": "Idukki",
      "capacity": 50,
      "data": [
        {
          "date": "04.06.2026",
          "waterLevel": "1193.39",
          "liveStorage": "7.24",
          "storagePercentage": "14.53",
          "inflow": "0.95",
          "powerHouseDischarge": "",
          "spillwayRelease": "–",
          "totalOutflow": "0",
          "rainfall": "10.00"
        }
      ]
    },
    {
      "id": "8",
      "name": "Ponmudi",
      "date": "04.06.2026",
      "level": 209.34,
      "inflow": 1.07,
      "outflow": 12.4,
      "rainfall": 0.67,
      "status": "9.79",
      "frl": 215.72,
      "mwl": null,
      "lat": 9.9604,
      "lon": 77.0565,
      "district": "Idukki",
      "capacity": 42,
      "data": [
        {
          "date": "04.06.2026",
          "waterLevel": "686.80",
          "liveStorage": "9.79",
          "storagePercentage": "20.66",
          "inflow": "1.07",
          "powerHouseDischarge": "0.67",
          "spillwayRelease": "–",
          "totalOutflow": "0.67",
          "rainfall": "29.00"
        }
      ]
    },
    {
      "id": "9",
      "name": "Kakkayam",
      "date": "04.06.2026",
      "level": 227.73,
      "inflow": 0.9,
      "outflow": 10.47,
      "rainfall": 0.7,
      "status": "10.64",
      "frl": 231.05,
      "mwl": null,
      "lat": 11.551,
      "lon": 75.925,
      "district": "Kozhikode",
      "capacity": 136,
      "data": [
        {
          "date": "04.06.2026",
          "waterLevel": "747.13",
          "liveStorage": "10.64",
          "storagePercentage": "31.32",
          "inflow": "0.90",
          "powerHouseDischarge": "0.70",
          "spillwayRelease": "–",
          "totalOutflow": "0.70",
          "rainfall": "12.00"
        }
      ]
    },
    {
      "id": "10",
      "name": "Pamba",
      "date": "04.06.2026",
      "level": 294.03,
      "inflow": 2.04,
      "outflow": 23.59,
      "rainfall": null,
      "status": "1.13",
      "frl": 300.63,
      "mwl": null,
      "lat": 9.3906,
      "lon": 77.1598,
      "district": "Pathanamthitta",
      "capacity": 37,
      "data": [
        {
          "date": "04.06.2026",
          "waterLevel": "964.65",
          "liveStorage": "1.13",
          "storagePercentage": "3.63",
          "inflow": "2.04",
          "powerHouseDischarge": "",
          "spillwayRelease": "–",
          "totalOutflow": "0.00",
          "rainfall": "104.00"
        }
      ]
    },
    {
      "id": "11",
      "name": "Poringalkuthu",
      "date": "04.06.2026",
      "level": 126,
      "inflow": 0.11,
      "outflow": 1.25,
      "rainfall": 1.01,
      "status": "7.05",
      "frl": 129.23,
      "mwl": null,
      "lat": 10.3436,
      "lon": 76.7438,
      "district": "Thrissur",
      "capacity": 328,
      "data": [
        {
          "date": "04.06.2026",
          "waterLevel": "413.40",
          "liveStorage": "7.05",
          "storagePercentage": "23.27",
          "inflow": "0.11",
          "powerHouseDischarge": "1.01",
          "spillwayRelease": "–",
          "totalOutflow": "1.01",
          "rainfall": "37.00"
        }
      ]
    },
    {
      "id": "12",
      "name": "Kundala",
      "date": "04.06.2026",
      "level": 530.66,
      "inflow": 0.37,
      "outflow": 4.34,
      "rainfall": null,
      "status": "0.09",
      "frl": 536.05,
      "mwl": null,
      "lat": 10.1436,
      "lon": 77.1986,
      "district": "Idukki",
      "capacity": 14,
      "data": [
        {
          "date": "04.06.2026",
          "waterLevel": "1741.00",
          "liveStorage": "0.09",
          "storagePercentage": "1.18",
          "inflow": "0.37",
          "powerHouseDischarge": "0.00",
          "spillwayRelease": "–",
          "totalOutflow": "0.00",
          "rainfall": "8.60"
        }
      ]
    },
    {
      "id": "13",
      "name": "Kallarkutty",
      "date": "04.06.2026",
      "level": 138.27,
      "inflow": 1.5,
      "outflow": 17.32,
      "rainfall": 1.22,
      "status": "4.60",
      "frl": 139.17,
      "mwl": null,
      "lat": 9.98,
      "lon": 77.0014,
      "district": "Idukki",
      "capacity": 44,
      "data": [
        {
          "date": "04.06.2026",
          "waterLevel": "453.65",
          "liveStorage": "4.60",
          "storagePercentage": "71.57",
          "inflow": "1.50",
          "powerHouseDischarge": "1.22",
          "spillwayRelease": "–",
          "totalOutflow": "1.22",
          "rainfall": "23.00"
        }
      ]
    },
    {
      "id": "14",
      "name": "Erattayar",
      "date": "04.06.2026",
      "level": 227.32,
      "inflow": null,
      "outflow": null,
      "rainfall": null,
      "status": "0.43",
      "frl": 229.94,
      "mwl": null,
      "lat": 9.8103,
      "lon": 77.106,
      "district": "Idukki",
      "capacity": 65,
      "data": [
        {
          "date": "04.06.2026",
          "waterLevel": "745.80",
          "liveStorage": "0.43",
          "storagePercentage": "8.05",
          "inflow": "",
          "powerHouseDischarge": "",
          "spillwayRelease": "–",
          "totalOutflow": "0.00",
          "rainfall": "0.00"
        }
      ]
    },
    {
      "id": "15",
      "name": "Pambla",
      "date": "04.06.2026",
      "level": 75.68,
      "inflow": 1.15,
      "outflow": 13.3,
      "rainfall": 1,
      "status": "2.63",
      "frl": 77.11,
      "mwl": null,
      "lat": 9.962,
      "lon": 76.9568,
      "district": "Ernakulam",
      "capacity": 23,
      "data": [
        {
          "date": "04.06.2026",
          "waterLevel": "248.30",
          "liveStorage": "2.63",
          "storagePercentage": "57.74",
          "inflow": "1.15",
          "powerHouseDischarge": "1.00",
          "spillwayRelease": "–",
          "totalOutflow": "1.00",
          "rainfall": "35.00"
        }
      ]
    },
    {
      "id": "16",
      "name": "Moozhiyar",
      "date": "04.06.2026",
      "level": 57.26,
      "inflow": 1.49,
      "outflow": 17.28,
      "rainfall": 1.52,
      "status": "0.55",
      "frl": 58.71,
      "mwl": null,
      "lat": 9.308,
      "lon": 77.0656,
      "district": "Pathanamthitta",
      "capacity": 90,
      "data": [
        {
          "date": "04.06.2026",
          "waterLevel": "187.85",
          "liveStorage": "0.55",
          "storagePercentage": "47.76",
          "inflow": "1.49",
          "powerHouseDischarge": "1.52",
          "spillwayRelease": "–",
          "totalOutflow": "1.52",
          "rainfall": "25.00"
        }
      ]
    },
    {
      "id": "17",
      "name": "Kallar",
      "date": "04.06.2026",
      "level": 249.81,
      "inflow": null,
      "outflow": null,
      "rainfall": null,
      "status": "0.16",
      "frl": 251.3,
      "mwl": null,
      "lat": 9.8255,
      "lon": 77.1562,
      "district": "Idukki",
      "capacity": 14,
      "data": [
        {
          "date": "04.06.2026",
          "waterLevel": "819.60",
          "liveStorage": "0.16",
          "storagePercentage": "21.28",
          "inflow": "",
          "powerHouseDischarge": "",
          "spillwayRelease": "–",
          "totalOutflow": "0.00",
          "rainfall": "0.00"
        }
      ]
    },
    {
      "id": "18",
      "name": "Chenkulam",
      "date": "04.06.2026",
      "level": 258.09,
      "inflow": 0.61,
      "outflow": 7.11,
      "rainfall": 0.68,
      "status": "0.18",
      "frl": 258.36,
      "mwl": null,
      "lat": 10.0108,
      "lon": 77.0325,
      "district": "Idukki",
      "capacity": 16,
      "data": [
        {
          "date": "04.06.2026",
          "waterLevel": "846.75",
          "liveStorage": "0.18",
          "storagePercentage": "45.56",
          "inflow": "0.61",
          "powerHouseDischarge": "0.68",
          "spillwayRelease": "–",
          "totalOutflow": "0.68",
          "rainfall": "6.30"
        }
      ]
    }
  ]
}