{
  "lastUpdate": "17.03.2026",
  "dams": [
    {
      "id": "1",
      "name": "Idukki",
      "date": "17.03.2026",
      "level": 717.19,
      "inflow": 0.94,
      "outflow": 10.93,
      "rainfall": 6.46,
      "status": "705.95",
      "frl": 732.43,
      "mwl": 732.43,
      "lat": 9.8436,
      "lon": 76.9762,
      "district": "Idukki",
      "capacity": 1996,
      "data": [
        {
          "date": "17.03.2026",
          "waterLevel": "2352.98 ft",
          "liveStorage": "705.95",
          "storagePercentage": "48.37",
          "inflow": "0.94",
          "powerHouseDischarge": "6.46",
          "spillwayRelease": "–",
          "totalOutflow": "6.46",
          "rainfall": "9.80"
        }
      ]
    },
    {
      "id": "2",
      "name": "Idamalayar",
      "date": "17.03.2026",
      "level": 44.54,
      "inflow": 0.07,
      "outflow": 0.81,
      "rainfall": 3.14,
      "status": "430.94",
      "frl": 51.51,
      "mwl": 51.51,
      "lat": 10.2219,
      "lon": 76.706,
      "district": "Ernakulam",
      "capacity": 1010,
      "data": [
        {
          "date": "17.03.2026",
          "waterLevel": "146.14",
          "liveStorage": "430.94",
          "storagePercentage": "42.34",
          "inflow": "0.07",
          "powerHouseDischarge": "3.14",
          "spillwayRelease": "–",
          "totalOutflow": "3.14",
          "rainfall": "0.00"
        }
      ]
    },
    {
      "id": "4",
      "name": "Banasura Sagar",
      "date": "17.03.2026",
      "level": 232.88,
      "inflow": 0.03,
      "outflow": 0.36,
      "rainfall": null,
      "status": "76.15",
      "frl": 236.4,
      "mwl": 236.4,
      "lat": 11.6709,
      "lon": 75.9504,
      "district": "Wayanad",
      "capacity": 209,
      "data": [
        {
          "date": "17.03.2026",
          "waterLevel": "764.05",
          "liveStorage": "76.15",
          "storagePercentage": "37.89",
          "inflow": "0.03",
          "powerHouseDischarge": "",
          "spillwayRelease": "–",
          "totalOutflow": "0.00",
          "rainfall": "0.00"
        }
      ]
    },
    {
      "id": "5",
      "name": "Sholayar",
      "date": "17.03.2026",
      "level": 803.64,
      "inflow": 0.27,
      "outflow": 3.1,
      "rainfall": 1.45,
      "status": "86.27",
      "frl": 811.68,
      "mwl": null,
      "lat": 10.3178,
      "lon": 76.7342,
      "district": "Thrissur",
      "capacity": 1530,
      "data": [
        {
          "date": "17.03.2026",
          "waterLevel": "2636.60 ft",
          "liveStorage": "86.27",
          "storagePercentage": "57.86",
          "inflow": "0.27",
          "powerHouseDischarge": "1.45",
          "spillwayRelease": "–",
          "totalOutflow": "1.45",
          "rainfall": "0.00"
        }
      ]
    },
    {
      "id": "6",
      "name": "Mattupetty",
      "date": "17.03.2026",
      "level": 484.31,
      "inflow": 0.11,
      "outflow": 1.23,
      "rainfall": null,
      "status": "29.24",
      "frl": 487.56,
      "mwl": null,
      "lat": 10.1063,
      "lon": 77.1238,
      "district": "Idukki",
      "capacity": 55,
      "data": [
        {
          "date": "17.03.2026",
          "waterLevel": "1588.95",
          "liveStorage": "29.24",
          "storagePercentage": "53.39",
          "inflow": "0.11",
          "powerHouseDischarge": "0.00",
          "spillwayRelease": "–",
          "totalOutflow": "0.00",
          "rainfall": "0.00"
        }
      ]
    },
    {
      "id": "7",
      "name": "Anayirankal",
      "date": "17.03.2026",
      "level": 367.9,
      "inflow": null,
      "outflow": null,
      "rainfall": null,
      "status": "49.84",
      "frl": 367.9,
      "mwl": null,
      "lat": 10.0095,
      "lon": 77.2072,
      "district": "Idukki",
      "capacity": 50,
      "data": [
        {
          "date": "17.03.2026",
          "waterLevel": "1207.02",
          "liveStorage": "49.84",
          "storagePercentage": "100.02",
          "inflow": "0.00",
          "powerHouseDischarge": "",
          "spillwayRelease": "–",
          "totalOutflow": "0",
          "rainfall": "0.00"
        }
      ]
    },
    {
      "id": "8",
      "name": "Ponmudi",
      "date": "17.03.2026",
      "level": 213.92,
      "inflow": 0.03,
      "outflow": 0.3,
      "rainfall": 0.82,
      "status": "33.86",
      "frl": 215.72,
      "mwl": null,
      "lat": 9.9604,
      "lon": 77.0565,
      "district": "Idukki",
      "capacity": 42,
      "data": [
        {
          "date": "17.03.2026",
          "waterLevel": "701.85",
          "liveStorage": "33.86",
          "storagePercentage": "71.43",
          "inflow": "0.03",
          "powerHouseDischarge": "0.82",
          "spillwayRelease": "–",
          "totalOutflow": "0.82",
          "rainfall": "0.00"
        }
      ]
    },
    {
      "id": "9",
      "name": "Kakkayam",
      "date": "17.03.2026",
      "level": 229.44,
      "inflow": 1.05,
      "outflow": 12.16,
      "rainfall": 1.36,
      "status": "21.32",
      "frl": 231.05,
      "mwl": null,
      "lat": 11.551,
      "lon": 75.925,
      "district": "Kozhikode",
      "capacity": 136,
      "data": [
        {
          "date": "17.03.2026",
          "waterLevel": "752.76",
          "liveStorage": "21.32",
          "storagePercentage": "62.74",
          "inflow": "1.05",
          "powerHouseDischarge": "1.36",
          "spillwayRelease": "–",
          "totalOutflow": "1.36",
          "rainfall": "0.00"
        }
      ]
    },
    {
      "id": "10",
      "name": "Pamba",
      "date": "17.03.2026",
      "level": 293.96,
      "inflow": 0.05,
      "outflow": 0.6,
      "rainfall": null,
      "status": "0.97",
      "frl": 300.63,
      "mwl": null,
      "lat": 9.3906,
      "lon": 77.1598,
      "district": "Pathanamthitta",
      "capacity": 37,
      "data": [
        {
          "date": "17.03.2026",
          "waterLevel": "964.45",
          "liveStorage": "0.97",
          "storagePercentage": "3.11",
          "inflow": "0.05",
          "powerHouseDischarge": "",
          "spillwayRelease": "–",
          "totalOutflow": "0.00",
          "rainfall": "20.00"
        }
      ]
    },
    {
      "id": "11",
      "name": "Poringalkuthu",
      "date": "17.03.2026",
      "level": 126.96,
      "inflow": 1.24,
      "outflow": 14.34,
      "rainfall": 1.14,
      "status": "12.20",
      "frl": 129.23,
      "mwl": null,
      "lat": 10.3436,
      "lon": 76.7438,
      "district": "Thrissur",
      "capacity": 328,
      "data": [
        {
          "date": "17.03.2026",
          "waterLevel": "416.55",
          "liveStorage": "12.20",
          "storagePercentage": "40.26",
          "inflow": "1.24",
          "powerHouseDischarge": "1.14",
          "spillwayRelease": "–",
          "totalOutflow": "1.14",
          "rainfall": "0.00"
        }
      ]
    },
    {
      "id": "12",
      "name": "Kundala",
      "date": "17.03.2026",
      "level": 535.99,
      "inflow": 0.03,
      "outflow": 0.34,
      "rainfall": null,
      "status": "7.28",
      "frl": 536.05,
      "mwl": null,
      "lat": 10.1436,
      "lon": 77.1986,
      "district": "Idukki",
      "capacity": 14,
      "data": [
        {
          "date": "17.03.2026",
          "waterLevel": "1758.50",
          "liveStorage": "7.28",
          "storagePercentage": "95.16",
          "inflow": "0.03",
          "powerHouseDischarge": "0.00",
          "spillwayRelease": "0.03",
          "totalOutflow": "0.03",
          "rainfall": "0.00"
        }
      ]
    },
    {
      "id": "13",
      "name": "Kallarkutty",
      "date": "17.03.2026",
      "level": 138.39,
      "inflow": 1.16,
      "outflow": 13.45,
      "rainfall": 1.13,
      "status": "4.86",
      "frl": 139.17,
      "mwl": null,
      "lat": 9.98,
      "lon": 77.0014,
      "district": "Idukki",
      "capacity": 44,
      "data": [
        {
          "date": "17.03.2026",
          "waterLevel": "454.05",
          "liveStorage": "4.86",
          "storagePercentage": "75.52",
          "inflow": "1.16",
          "powerHouseDischarge": "1.13",
          "spillwayRelease": "–",
          "totalOutflow": "1.13",
          "rainfall": "0.00"
        }
      ]
    },
    {
      "id": "14",
      "name": "Erattayar",
      "date": "17.03.2026",
      "level": 227.53,
      "inflow": null,
      "outflow": null,
      "rainfall": null,
      "status": "0.79",
      "frl": 229.94,
      "mwl": null,
      "lat": 9.8103,
      "lon": 77.106,
      "district": "Idukki",
      "capacity": 65,
      "data": [
        {
          "date": "17.03.2026",
          "waterLevel": "746.50",
          "liveStorage": "0.79",
          "storagePercentage": "14.94",
          "inflow": "",
          "powerHouseDischarge": "",
          "spillwayRelease": "–",
          "totalOutflow": "0.00",
          "rainfall": "0.00"
        }
      ]
    },
    {
      "id": "15",
      "name": "Pambla",
      "date": "17.03.2026",
      "level": 76.54,
      "inflow": 1.35,
      "outflow": 15.63,
      "rainfall": 1.39,
      "status": "3.74",
      "frl": 77.11,
      "mwl": null,
      "lat": 9.962,
      "lon": 76.9568,
      "district": "Ernakulam",
      "capacity": 23,
      "data": [
        {
          "date": "17.03.2026",
          "waterLevel": "251.10",
          "liveStorage": "3.74",
          "storagePercentage": "82.24",
          "inflow": "1.35",
          "powerHouseDischarge": "1.39",
          "spillwayRelease": "–",
          "totalOutflow": "1.39",
          "rainfall": "0.00"
        }
      ]
    },
    {
      "id": "16",
      "name": "Moozhiyar",
      "date": "17.03.2026",
      "level": 57.67,
      "inflow": 2.18,
      "outflow": 25.22,
      "rainfall": 2.17,
      "status": "0.70",
      "frl": 58.71,
      "mwl": null,
      "lat": 9.308,
      "lon": 77.0656,
      "district": "Pathanamthitta",
      "capacity": 90,
      "data": [
        {
          "date": "17.03.2026",
          "waterLevel": "189.20",
          "liveStorage": "0.70",
          "storagePercentage": "60.69",
          "inflow": "2.18",
          "powerHouseDischarge": "2.17",
          "spillwayRelease": "–",
          "totalOutflow": "2.17",
          "rainfall": "0.00"
        }
      ]
    },
    {
      "id": "17",
      "name": "Kallar",
      "date": "17.03.2026",
      "level": 249.66,
      "inflow": null,
      "outflow": null,
      "rainfall": null,
      "status": "0.79",
      "frl": 251.3,
      "mwl": null,
      "lat": 9.8255,
      "lon": 77.1562,
      "district": "Idukki",
      "capacity": 14,
      "data": [
        {
          "date": "17.03.2026",
          "waterLevel": "819.10",
          "liveStorage": "0.79",
          "storagePercentage": "103.63",
          "inflow": "",
          "powerHouseDischarge": "",
          "spillwayRelease": "–",
          "totalOutflow": "0.00",
          "rainfall": "0.00"
        }
      ]
    },
    {
      "id": "18",
      "name": "Chenkulam",
      "date": "17.03.2026",
      "level": 258.18,
      "inflow": 0.71,
      "outflow": 8.19,
      "rainfall": 0.7,
      "status": "0.25",
      "frl": 258.36,
      "mwl": null,
      "lat": 10.0108,
      "lon": 77.0325,
      "district": "Idukki",
      "capacity": 16,
      "data": [
        {
          "date": "17.03.2026",
          "waterLevel": "847.05",
          "liveStorage": "0.25",
          "storagePercentage": "63.59",
          "inflow": "0.71",
          "powerHouseDischarge": "0.70",
          "spillwayRelease": "–",
          "totalOutflow": "0.70",
          "rainfall": "0.00"
        }
      ]
    }
  ]
}