{
  "lastUpdate": "24.09.2025",
  "dams": [
    {
      "id": "1",
      "name": "Idukki",
      "date": "24.09.2025",
      "level": 725.47,
      "inflow": 3.83,
      "outflow": 44.27,
      "rainfall": 5.03,
      "status": "1078.50",
      "frl": 732.43,
      "mwl": 730.59,
      "lat": 9.8436,
      "lon": 76.9762,
      "district": "Idukki",
      "capacity": 1996,
      "data": [
        {
          "date": "24.09.2025",
          "waterLevel": "2380.14 ft",
          "liveStorage": "1078.50",
          "storagePercentage": "73.90",
          "inflow": "3.83",
          "powerHouseDischarge": "5.03",
          "spillwayRelease": "–",
          "totalOutflow": "5.03",
          "rainfall": "13.60"
        }
      ]
    },
    {
      "id": "2",
      "name": "Idamalayar",
      "date": "24.09.2025",
      "level": 49.37,
      "inflow": 2.5,
      "outflow": 28.92,
      "rainfall": 5.03,
      "status": "815.73",
      "frl": 51.51,
      "mwl": 50.69,
      "lat": 10.2219,
      "lon": 76.706,
      "district": "Ernakulam",
      "capacity": 1010,
      "data": [
        {
          "date": "24.09.2025",
          "waterLevel": "161.98",
          "liveStorage": "815.73",
          "storagePercentage": "80.15",
          "inflow": "2.50",
          "powerHouseDischarge": "5.03",
          "spillwayRelease": "–",
          "totalOutflow": "5.03",
          "rainfall": "5.60"
        }
      ]
    },
    {
      "id": "4",
      "name": "Banasura Sagar",
      "date": "24.09.2025",
      "level": 235.98,
      "inflow": 0.62,
      "outflow": 7.18,
      "rainfall": 1.12,
      "status": "183.75",
      "frl": 236.4,
      "mwl": 236.22,
      "lat": 11.6709,
      "lon": 75.9504,
      "district": "Wayanad",
      "capacity": 209,
      "data": [
        {
          "date": "24.09.2025",
          "waterLevel": "774.20",
          "liveStorage": "183.75",
          "storagePercentage": "91.42",
          "inflow": "0.62",
          "powerHouseDischarge": "1.12",
          "spillwayRelease": "–",
          "totalOutflow": "1.12",
          "rainfall": "2.00"
        }
      ]
    },
    {
      "id": "5",
      "name": "Sholayar",
      "date": "24.09.2025",
      "level": 811.38,
      "inflow": 1.26,
      "outflow": 14.63,
      "rainfall": 1.26,
      "status": "146.26",
      "frl": 811.68,
      "mwl": null,
      "lat": 10.3178,
      "lon": 76.7342,
      "district": "Thrissur",
      "capacity": 1530,
      "data": [
        {
          "date": "24.09.2025",
          "waterLevel": "2662.00 ft",
          "liveStorage": "146.26",
          "storagePercentage": "98.10",
          "inflow": "1.26",
          "powerHouseDischarge": "1.26",
          "spillwayRelease": "–",
          "totalOutflow": "1.26",
          "rainfall": "22.20"
        }
      ]
    },
    {
      "id": "6",
      "name": "Mattupetty",
      "date": "24.09.2025",
      "level": 486.72,
      "inflow": 0.98,
      "outflow": 11.3,
      "rainfall": null,
      "status": "46.57",
      "frl": 487.56,
      "mwl": null,
      "lat": 10.1063,
      "lon": 77.1238,
      "district": "Idukki",
      "capacity": 55,
      "data": [
        {
          "date": "24.09.2025",
          "waterLevel": "1596.85",
          "liveStorage": "46.57",
          "storagePercentage": "85.02",
          "inflow": "0.98",
          "powerHouseDischarge": "0.00",
          "spillwayRelease": "0.95",
          "totalOutflow": "0.95",
          "rainfall": "2.40"
        }
      ]
    },
    {
      "id": "7",
      "name": "Anayirankal",
      "date": "24.09.2025",
      "level": 367.66,
      "inflow": 0.09,
      "outflow": 1.01,
      "rainfall": null,
      "status": "46.33",
      "frl": 367.9,
      "mwl": null,
      "lat": 10.0095,
      "lon": 77.2072,
      "district": "Idukki",
      "capacity": 50,
      "data": [
        {
          "date": "24.09.2025",
          "waterLevel": "1206.22",
          "liveStorage": "46.33",
          "storagePercentage": "92.98",
          "inflow": "0.09",
          "powerHouseDischarge": "",
          "spillwayRelease": "–",
          "totalOutflow": "1.00",
          "rainfall": "0.00"
        }
      ]
    },
    {
      "id": "8",
      "name": "Ponmudi",
      "date": "24.09.2025",
      "level": 213.31,
      "inflow": 1.11,
      "outflow": 12.85,
      "rainfall": 1.41,
      "status": "29.88",
      "frl": 215.72,
      "mwl": null,
      "lat": 9.9604,
      "lon": 77.0565,
      "district": "Idukki",
      "capacity": 42,
      "data": [
        {
          "date": "24.09.2025",
          "waterLevel": "699.85",
          "liveStorage": "29.88",
          "storagePercentage": "63.04",
          "inflow": "1.11",
          "powerHouseDischarge": "1.41",
          "spillwayRelease": "–",
          "totalOutflow": "1.41",
          "rainfall": "9.00"
        }
      ]
    },
    {
      "id": "9",
      "name": "Kakkayam",
      "date": "24.09.2025",
      "level": 229.51,
      "inflow": 1.65,
      "outflow": 19.05,
      "rainfall": 1.53,
      "status": "21.74",
      "frl": 231.05,
      "mwl": null,
      "lat": 11.551,
      "lon": 75.925,
      "district": "Kozhikode",
      "capacity": 136,
      "data": [
        {
          "date": "24.09.2025",
          "waterLevel": "752.98",
          "liveStorage": "21.74",
          "storagePercentage": "63.99",
          "inflow": "1.65",
          "powerHouseDischarge": "1.53",
          "spillwayRelease": "–",
          "totalOutflow": "1.53",
          "rainfall": "5.00"
        }
      ]
    },
    {
      "id": "10",
      "name": "Pamba",
      "date": "24.09.2025",
      "level": 297.29,
      "inflow": 0.45,
      "outflow": 5.21,
      "rainfall": null,
      "status": "12.66",
      "frl": 300.63,
      "mwl": null,
      "lat": 9.3906,
      "lon": 77.1598,
      "district": "Pathanamthitta",
      "capacity": 37,
      "data": [
        {
          "date": "24.09.2025",
          "waterLevel": "975.35",
          "liveStorage": "12.66",
          "storagePercentage": "40.64",
          "inflow": "0.45",
          "powerHouseDischarge": "",
          "spillwayRelease": "–",
          "totalOutflow": "0.00",
          "rainfall": "12.00"
        }
      ]
    },
    {
      "id": "11",
      "name": "Poringalkuthu",
      "date": "24.09.2025",
      "level": 127.15,
      "inflow": 2.63,
      "outflow": 30.42,
      "rainfall": 2.13,
      "status": "13.40",
      "frl": 129.23,
      "mwl": null,
      "lat": 10.3436,
      "lon": 76.7438,
      "district": "Thrissur",
      "capacity": 328,
      "data": [
        {
          "date": "24.09.2025",
          "waterLevel": "417.15",
          "liveStorage": "13.40",
          "storagePercentage": "44.22",
          "inflow": "2.63",
          "powerHouseDischarge": "2.13",
          "spillwayRelease": "–",
          "totalOutflow": "2.13",
          "rainfall": "7.00"
        }
      ]
    },
    {
      "id": "12",
      "name": "Kundala",
      "date": "24.09.2025",
      "level": 535.84,
      "inflow": 0.03,
      "outflow": 0.34,
      "rainfall": null,
      "status": "6.90",
      "frl": 536.05,
      "mwl": null,
      "lat": 10.1436,
      "lon": 77.1986,
      "district": "Idukki",
      "capacity": 14,
      "data": [
        {
          "date": "24.09.2025",
          "waterLevel": "1758.00",
          "liveStorage": "6.90",
          "storagePercentage": "90.20",
          "inflow": "0.03",
          "powerHouseDischarge": "",
          "spillwayRelease": "0.03",
          "totalOutflow": "0.03",
          "rainfall": "0.00"
        }
      ]
    },
    {
      "id": "13",
      "name": "Kallarkutty",
      "date": "24.09.2025",
      "level": 132.6,
      "inflow": 2.71,
      "outflow": 31.36,
      "rainfall": 2.94,
      "status": "4.24",
      "frl": 139.17,
      "mwl": null,
      "lat": 9.98,
      "lon": 77.0014,
      "district": "Idukki",
      "capacity": 44,
      "data": [
        {
          "date": "24.09.2025",
          "waterLevel": "435.05",
          "liveStorage": "4.24",
          "storagePercentage": "66.00",
          "inflow": "2.71",
          "powerHouseDischarge": "2.94",
          "spillwayRelease": "–",
          "totalOutflow": "2.94",
          "rainfall": "15.00"
        }
      ]
    },
    {
      "id": "14",
      "name": "Erattayar",
      "date": "24.09.2025",
      "level": 227.69,
      "inflow": null,
      "outflow": null,
      "rainfall": null,
      "status": "0.94",
      "frl": 229.94,
      "mwl": null,
      "lat": 9.8103,
      "lon": 77.106,
      "district": "Idukki",
      "capacity": 65,
      "data": [
        {
          "date": "24.09.2025",
          "waterLevel": "747.00",
          "liveStorage": "0.94",
          "storagePercentage": "17.70",
          "inflow": "",
          "powerHouseDischarge": "",
          "spillwayRelease": "",
          "totalOutflow": "0.00",
          "rainfall": ""
        }
      ]
    },
    {
      "id": "15",
      "name": "Pambla",
      "date": "24.09.2025",
      "level": 75.74,
      "inflow": 4.45,
      "outflow": 51.51,
      "rainfall": 3.74,
      "status": "2.71",
      "frl": 77.11,
      "mwl": null,
      "lat": 9.962,
      "lon": 76.9568,
      "district": "Ernakulam",
      "capacity": 23,
      "data": [
        {
          "date": "24.09.2025",
          "waterLevel": "248.50",
          "liveStorage": "2.71",
          "storagePercentage": "59.45",
          "inflow": "4.45",
          "powerHouseDischarge": "3.74",
          "spillwayRelease": "–",
          "totalOutflow": "3.74",
          "rainfall": "18.00"
        }
      ]
    },
    {
      "id": "16",
      "name": "Moozhiyar",
      "date": "24.09.2025",
      "level": 57.81,
      "inflow": 3.32,
      "outflow": 38.42,
      "rainfall": 2.19,
      "status": "0.76",
      "frl": 58.71,
      "mwl": null,
      "lat": 9.308,
      "lon": 77.0656,
      "district": "Pathanamthitta",
      "capacity": 90,
      "data": [
        {
          "date": "24.09.2025",
          "waterLevel": "189.65",
          "liveStorage": "0.76",
          "storagePercentage": "65.09",
          "inflow": "3.32",
          "powerHouseDischarge": "2.19",
          "spillwayRelease": "–",
          "totalOutflow": "2.19",
          "rainfall": "12.00"
        }
      ]
    },
    {
      "id": "17",
      "name": "Kallar",
      "date": "24.09.2025",
      "level": 250.03,
      "inflow": null,
      "outflow": null,
      "rainfall": null,
      "status": "0.20",
      "frl": 251.3,
      "mwl": null,
      "lat": 9.8255,
      "lon": 77.1562,
      "district": "Idukki",
      "capacity": 14,
      "data": [
        {
          "date": "24.09.2025",
          "waterLevel": "820.30",
          "liveStorage": "0.20",
          "storagePercentage": "25.62",
          "inflow": "",
          "powerHouseDischarge": "",
          "spillwayRelease": "–",
          "totalOutflow": "0.00",
          "rainfall": ""
        }
      ]
    },
    {
      "id": "18",
      "name": "Chenkulam",
      "date": "24.09.2025",
      "level": 258.12,
      "inflow": 1.15,
      "outflow": 13.35,
      "rainfall": 1.09,
      "status": "0.20",
      "frl": 258.36,
      "mwl": null,
      "lat": 10.0108,
      "lon": 77.0325,
      "district": "Idukki",
      "capacity": 16,
      "data": [
        {
          "date": "24.09.2025",
          "waterLevel": "846.85",
          "liveStorage": "0.20",
          "storagePercentage": "51.54",
          "inflow": "1.15",
          "powerHouseDischarge": "1.09",
          "spillwayRelease": "–",
          "totalOutflow": "1.09",
          "rainfall": "4.00"
        }
      ]
    }
  ]
}